Metadata-Version: 2.1
Name: sqlalchemy-dremio-flight
Version: 1.2.6
Summary: A SQLAlchemy dialect for Dremio via Flight interface.
Home-page: https://github.com/weltam/sqlalchemy_dremio
Author: Welly Tambunan
Author-email: coach@wellytambunan.com
License: Apache Software License
Keywords: sqlalchemy_dremio_flight
Platform: UNKNOWN
Classifier: Development Status :: 5 - Production/Stable
Classifier: Intended Audience :: Developers
Classifier: License :: OSI Approved :: Apache Software License
Classifier: Natural Language :: English
Classifier: Programming Language :: Python :: 3
Classifier: Programming Language :: Python :: 3.7
License-File: LICENSE
